setup.py
all_stats_distributions/Binomialdistribution.py
all_stats_distributions/Gaussiandistribution.py
all_stats_distributions/Generaldistribution.py
all_stats_distributions/__init__.py
all_stats_distributions.egg-info/PKG-INFO
all_stats_distributions.egg-info/SOURCES.txt
all_stats_distributions.egg-info/dependency_links.txt
all_stats_distributions.egg-info/not-zip-safe
all_stats_distributions.egg-info/top_level.txt