Metadata-Version: 1.0
Name: all-stats-distributions
Version: 0.1
Summary: Gaussian distributions
Home-page: UNKNOWN
Author: Shashank Raj
Author-email: shashank.raj2009@gmail.com
License: UNKNOWN
Platform: UNKNOWN
